syncrypto/filetree.py
syncrypto/__main__.py
syncrypto/core.py
syncrypto/__init__.py
syncrypto/crypto.py
syncrypto/util.py
syncrypto/cli.py
syncrypto/package_info.py
syncrypto-0.4.1.dist-info/entry_points.txt
syncrypto-0.4.1.dist-info/METADATA
syncrypto-0.4.1.dist-info/DESCRIPTION.rst
syncrypto-0.4.1.dist-info/metadata.json
syncrypto-0.4.1.dist-info/RECORD
syncrypto-0.4.1.dist-info/WHEEL
syncrypto-0.4.1.dist-info/top_level.txt
