Metadata-Version: 2.0
Name: syncrypto
Version: 0.4.1
Summary: 
Requires-Dist: cryptography
Requires-Dist: lockfile
